MANIFEST.in
README
README.wanted
setup.py
generalobj/__init__.py
generalobj/forms.py
generalobj/models.py
generalobj/urls.py
generalobj/utils.py
generalobj/views.py
generalobj.egg-info/PKG-INFO
generalobj.egg-info/SOURCES.txt
generalobj.egg-info/dependency_links.txt
generalobj.egg-info/not-zip-safe
generalobj.egg-info/requires.txt
generalobj.egg-info/top_level.txt
generalobj/management/__init__.py
generalobj/management/commands/__init__.py
generalobj/management/commands/import_gos_from_file.py
generalobj/migrations/0001_initial.py
generalobj/migrations/0002_auto_20210117_2150.py
generalobj/migrations/0003_auto_20210118_2319.py
generalobj/migrations/__init__.py
generalobj/templates/generalobj.html
generalobj/templates/generalobj_bulkedit.html
generalobj/templates/generalobj_new.html
generalobj/templates/generalobj_search.html
generalobj/templates/generalobjs.html
generalobj/templates/ajax/get_object_list.html
generalobj/templates/blocks/display_form.html
generalobj/templates/blocks/display_forms.html
generalobj/templates/blocks/download_excelsheet_modal.html
generalobj/templates/blocks/find_button_for_ajax_searches.html
generalobj/templatetags/__init__.py
generalobj/templatetags/extras.py