Metadata-Version: 2.1
Name: generalobj
Version: 0.10.24
Summary: Generalobj is a package for easy form handling for general Form Objects
Home-page: UNKNOWN
Author: Csaba Saranszky
Author-email: alt@256.hu
License: GPL
Platform: UNKNOWN
